{
  "parent": "extrasponges:recipes/root",
  "rewards": {
    "recipes": [
      "extrasponges:iron_sponge"
    ]
  },
  "criteria": {
    "has_iron_ingot": {
      "trigger": "minecraft:inventory_changed",
      "conditions": {
        "items": [
          {
            "items": [
              "minecraft:iron_ingot"
            ]
          }
        ]
      }
    },
    "has_the_recipe": {
      "trigger": "minecraft:recipe_unlocked",
      "conditions": {
        "recipe": "extrasponges:iron_sponge"
      }
    }
  },
  "requirements": [
    [
      "has_iron_ingot",
      "has_the_recipe"
    ]
  ]
}